nlgen/__init__.py
nlgen/compat.py
nlgen/exception.py
nlgen/cfg/__init__.py
nlgen/cfg/cfg.py
nlgen/cfg/feature.py
nlgen/cfg/markup.py
nlgen/cfg/markup_parser.py
nlgen/cfg/production.py
nlgen/cfg/result.py
nlgen/tests/__init__.py
nlgen/tests/cfg/__init__.py
nlgen/tests/cfg/test_cfg.py
nlgen/tests/cfg/test_feature.py
nlgen/tests/cfg/test_full.py
nlgen/tests/cfg/test_markup.py
nlgen/tests/cfg/test_production_list.py
nlgen/tests/cfg/test_production_ref.py
nlgen/tests/cfg/test_production_union.py
nlgen/tests/cfg/test_terminal.py
nlgen/tests/cfg/test_tutorial.py
nlgen-0.1.2.dist-info/DESCRIPTION.rst
nlgen-0.1.2.dist-info/METADATA
nlgen-0.1.2.dist-info/RECORD
nlgen-0.1.2.dist-info/WHEEL
nlgen-0.1.2.dist-info/entry_points.txt
nlgen-0.1.2.dist-info/metadata.json
nlgen-0.1.2.dist-info/top_level.txt
