Metadata-Version: 2.0
Name: nlgen
Version: 0.1.2
Summary: natural language generator
Home-page: UNKNOWN
Author: Yusuke Tsutsumi
Author-email: yusuke@tsutsumi.io
License: UNKNOWN
Platform: UNKNOWN
Classifier: Programming Language :: Python :: 3
Classifier: Programming Language :: Python :: 2
Classifier: Development Status :: 3 - Alpha
Classifier: License :: OSI Approved :: MIT License
Requires-Dist: grako
